asrp/__init__.py
asrp/code2voice.py
asrp/eval.py
asrp/glow.py
asrp/hifigan.py
asrp/interface.py
asrp/live.py
asrp/metric.py
asrp/preprocessing.py
asrp/s3prl_loader.py
asrp/seeak.py
asrp/speaker_embedding.py
asrp/speech_enhancement.py
asrp/tacotron2.py
asrp/test.py
asrp/utility.py
asrp/voice2code.py
asrp/code2voice_model/__init__.py
asrp/code2voice_model/hubert.py
asrp/code2voice_model/mhubert.py
asrp/denoiser/__init__.py
asrp/denoiser/demucs.py
asrp/denoiser/pretrained.py
asrp/denoiser/resample.py
asrp/denoiser/utils.py
asrp/voice2code_model/__init__.py
asrp/voice2code_model/hubert.py
asrp/voice2code_model/mhubert.py
asrp-0.0.75.dist-info/LICENSE
asrp-0.0.75.dist-info/METADATA
asrp-0.0.75.dist-info/WHEEL
asrp-0.0.75.dist-info/top_level.txt
asrp-0.0.75.dist-info/RECORD
