Metadata-Version: 2.1
Name: asrp
Version: 0.0.75
Home-page: https://github.com/voidful/asrp
Author: Voidful
Author-email: voidful.stack@gmail.com
License: Apache
Keywords: asr
Classifier: Development Status :: 4 - Beta
Classifier: License :: OSI Approved :: Apache Software License
Classifier: Programming Language :: Python
License-File: LICENSE
Requires-Dist: Unidecode
Requires-Dist: jiwer
Requires-Dist: transformers >=4.25.1
Requires-Dist: editdistance
Requires-Dist: librosa
Requires-Dist: webrtcvad
Requires-Dist: pyctcdecode
Requires-Dist: nlp2 >=1.8.49
